[
  {
    "id": "a1b2c3d4-5e6f-4a7b-8c9d-0e1f2a3b4c5d",
    "data": [
      {
        "text": "preciso descartar ",
        "userDefined": false
      },
      {
        "text": "Lata",
        "meta": "@metal_lixo",
        "alias": "metal_lixo",
        "userDefined": false
      }
    ],
    "isTemplate": false,
    "count": 1,
    "lang": "pt-br",
    "updated": 0
  },
  {
    "id": "b2c3d4e5-6f7a-4b8c-9d0e-1f2a3b4c5d6e",
    "data": [
      {
        "text": "onde jogo ",
        "userDefined": false
      },
      {
        "text": "lata",
        "meta": "@metal_lixo",
        "alias": "metal_lixo",
        "userDefined": false
      }
    ],
    "isTemplate": false,
    "count": 0,
    "lang": "pt-br",
    "updated": 0
  },
  {
    "id": "c3d4e5f6-7a8b-4c9d-0e1f-2a3b4c5d6e7f",
    "data": [
      {
        "text": "como descartar ",
        "userDefined": false
      },
      {
        "text": "latas",
        "meta": "@metal_lixo",
        "alias": "metal_lixo",
        "userDefined": false
      }
    ],
    "isTemplate": false,
    "count": 0,
    "lang": "pt-br",
    "updated": 0
  },
  {
    "id": "d4e5f6a7-8b9c-4d0e-1f2a-3b4c5d6e7f8a",
    "data": [
      {
        "text": "descartar ",
        "userDefined": false
      },
      {
        "text": "latinha",
        "meta": "@metal_lixo",
        "alias": "metal_lixo",
        "userDefined": false
      }
    ],
    "isTemplate": false,
    "count": 0,
    "lang": "pt-br",
    "updated": 0
  },
  {
    "id": "e5f6a7b8-9c0d-4e1f-2a3b-4c5d6e7f8a9b",
    "data": [
      {
        "text": "preciso jogar ",
        "userDefined": false
      },
      {
        "text": "lata de refrigerante",
        "meta": "@metal_lixo",
        "alias": "metal_lixo",
        "userDefined": false
      },
      {
        "text": " fora",
        "userDefined": false
      }
    ],
    "isTemplate": false,
    "count": 0,
    "lang": "pt-br",
    "updated": 0
  },
  {
    "id": "f6a7b8c9-0d1e-4f2a-3b4c-5d6e7f8a9b0c",
    "data": [
      {
        "text": "qual a lixeira para ",
        "userDefined": false
      },
      {
        "text": "lata de cerveja",
        "meta": "@metal_lixo",
        "alias": "metal_lixo",
        "userDefined": false
      }
    ],
    "isTemplate": false,
    "count": 0,
    "lang": "pt-br",
    "updated": 0
  },
  {
    "id": "0a1b2c3d-4e5f-4a6b-7c8d-9e0f1a2b3c4d",
    "data": [
      {
        "text": "onde coloco ",
        "userDefined": false
      },
      {
        "text": "lata de conserva",
        "meta": "@metal_lixo",
        "alias": "metal_lixo",
        "userDefined": false
      }
    ],
    "isTemplate": false,
    "count": 0,
    "lang": "pt-br",
    "updated": 0
  },
  {
    "id": "1b2c3d4e-5f6a-4b7c-8d9e-0f1a2b3c4d5e",
    "data": [
      {
        "text": "como descartar ",
        "userDefined": false
      },
      {
        "text": "lata de sardinha",
        "meta": "@metal_lixo",
        "alias": "metal_lixo",
        "userDefined": false
      }
    ],
    "isTemplate": false,
    "count": 0,
    "lang": "pt-br",
    "updated": 0
  },
  {
    "id": "2c3d4e5f-6a7b-4c8d-9e0f-1a2b3c4d5e6f",
    "data": [
      {
        "text": "preciso descartar ",
        "userDefined": false
      },
      {
        "text": "lata de atum",
        "meta": "@metal_lixo",
        "alias": "metal_lixo",
        "userDefined": false
      }
    ],
    "isTemplate": false,
    "count": 0,
    "lang": "pt-br",
    "updated": 0
  },
  {
    "id": "3d4e5f6a-7b8c-4d9e-0f1a-2b3c4d5e6f7a",
    "data": [
      {
        "text": "onde jogo ",
        "userDefined": false
      },
      {
        "text": "lata de milho",
        "meta": "@metal_lixo",
        "alias": "metal_lixo",
        "userDefined": false
      }
    ],
    "isTemplate": false,
    "count": 0,
    "lang": "pt-br",
    "updated": 0
  },
  {
    "id": "4e5f6a7b-8c9d-4e0f-1a2b-3c4d5e6f7a8b",
    "data": [
      {
        "text": "descartar ",
        "userDefined": false
      },
      {
        "text": "Alumínio",
        "meta": "@metal_lixo",
        "alias": "metal_lixo",
        "userDefined": false
      }
    ],
    "isTemplate": false,
    "count": 0,
    "lang": "pt-br",
    "updated": 0
  },
  {
    "id": "5f6a7b8c-9d0e-4f1a-2b3c-4d5e6f7a8b9c",
    "data": [
      {
        "text": "qual a lixeira para ",
        "userDefined": false
      },
      {
        "text": "aluminio",
        "meta": "@metal_lixo",
        "alias": "metal_lixo",
        "userDefined": false
      }
    ],
    "isTemplate": false,
    "count": 0,
    "lang": "pt-br",
    "updated": 0
  },
  {
    "id": "0a1b2c3d-4e5f-4a6b-7c8d-9e0f1a2b3c4e",
    "data": [
      {
        "text": "como jogar ",
        "userDefined": false
      },
      {
        "text": "alumínio",
        "meta": "@metal_lixo",
        "alias": "metal_lixo",
        "userDefined": false
      },
      {
        "text": " fora",
        "userDefined": false
      }
    ],
    "isTemplate": false,
    "count": 0,
    "lang": "pt-br",
    "updated": 0
  },
  {
    "id": "1b2c3d4e-5f6a-4b7c-8d9e-0f1a2b3c4d5f",
    "data": [
      {
        "text": "preciso me livrar de ",
        "userDefined": false
      },
      {
        "text": "Metal",
        "meta": "@metal_lixo",
        "alias": "metal_lixo",
        "userDefined": false
      }
    ],
    "isTemplate": false,
    "count": 0,
    "lang": "pt-br",
    "updated": 0
  },
  {
    "id": "2c3d4e5f-6a7b-4c8d-9e0f-1a2b3c4d5e60",
    "data": [
      {
        "text": "onde coloco ",
        "userDefined": false
      },
      {
        "text": "metal",
        "meta": "@metal_lixo",
        "alias": "metal_lixo",
        "userDefined": false
      }
    ],
    "isTemplate": false,
    "count": 0,
    "lang": "pt-br",
    "updated": 0
  },
  {
    "id": "3d4e5f6a-7b8c-4d9e-0f1a-2b3c4d5e6f70",
    "data": [
      {
        "text": "como descartar ",
        "userDefined": false
      },
      {
        "text": "metais",
        "meta": "@metal_lixo",
        "alias": "metal_lixo",
        "userDefined": false
      }
    ],
    "isTemplate": false,
    "count": 0,
    "lang": "pt-br",
    "updated": 0
  },
  {
    "id": "4e5f6a7b-8c9d-4e0f-1a2b-3c4d5e6f7a80",
    "data": [
      {
        "text": "descartar ",
        "userDefined": false
      },
      {
        "text": "metalico",
        "meta": "@metal_lixo",
        "alias": "metal_lixo",
        "userDefined": false
      }
    ],
    "isTemplate": false,
    "count": 0,
    "lang": "pt-br",
    "updated": 0
  },
  {
    "id": "5f6a7b8c-9d0e-4f1a-2b3c-4d5e6f7a8b90",
    "data": [
      {
        "text": "preciso descartar ",
        "userDefined": false
      },
      {
        "text": "metálico",
        "meta": "@metal_lixo",
        "alias": "metal_lixo",
        "userDefined": false
      }
    ],
    "isTemplate": false,
    "count": 0,
    "lang": "pt-br",
    "updated": 0
  },
  {
    "id": "0a1b2c3d-4e5f-4a6b-7c8d-9e0f1a2b3c4f",
    "data": [
      {
        "text": "onde jogo ",
        "userDefined": false
      },
      {
        "text": "Ferro",
        "meta": "@metal_lixo",
        "alias": "metal_lixo",
        "userDefined": false
      }
    ],
    "isTemplate": false,
    "count": 0,
    "lang": "pt-br",
    "updated": 0
  },
  {
    "id": "1b2c3d4e-5f6a-4b7c-8d9e-0f1a2b3c4d60",
    "data": [
      {
        "text": "qual a lixeira para ",
        "userDefined": false
      },
      {
        "text": "ferro",
        "meta": "@metal_lixo",
        "alias": "metal_lixo",
        "userDefined": false
      }
    ],
    "isTemplate": false,
    "count": 0,
    "lang": "pt-br",
    "updated": 0
  },
  {
    "id": "2c3d4e5f-6a7b-4c8d-9e0f-1a2b3c4d5e70",
    "data": [
      {
        "text": "como descartar ",
        "userDefined": false
      },
      {
        "text": "ferragem",
        "meta": "@metal_lixo",
        "alias": "metal_lixo",
        "userDefined": false
      }
    ],
    "isTemplate": false,
    "count": 0,
    "lang": "pt-br",
    "updated": 0
  },
  {
    "id": "3d4e5f6a-7b8c-4d9e-0f1a-2b3c4d5e6f80",
    "data": [
      {
        "text": "preciso jogar ",
        "userDefined": false
      },
      {
        "text": "Tampa de metal",
        "meta": "@metal_lixo",
        "alias": "metal_lixo",
        "userDefined": false
      },
      {
        "text": " fora",
        "userDefined": false
      }
    ],
    "isTemplate": false,
    "count": 0,
    "lang": "pt-br",
    "updated": 0
  },
  {
    "id": "4e5f6a7b-8c9d-4e0f-1a2b-3c4d5e6f7a90",
    "data": [
      {
        "text": "onde coloco ",
        "userDefined": false
      },
      {
        "text": "tampa de metal",
        "meta": "@metal_lixo",
        "alias": "metal_lixo",
        "userDefined": false
      }
    ],
    "isTemplate": false,
    "count": 0,
    "lang": "pt-br",
    "updated": 0
  },
  {
    "id": "5f6a7b8c-9d0e-4f1a-2b3c-4d5e6f7a8b00",
    "data": [
      {
        "text": "descartar ",
        "userDefined": false
      },
      {
        "text": "tampinha",
        "meta": "@metal_lixo",
        "alias": "metal_lixo",
        "userDefined": false
      }
    ],
    "isTemplate": false,
    "count": 0,
    "lang": "pt-br",
    "updated": 0
  },
  {
    "data": [
      {
        "text": "Alumínio",
        "meta": "@metal_lixo",
        "alias": "metal_lixo",
        "userDefined": false
      }
    ],
    "isTemplate": false,
    "count": 0,
    "lang": "pt-br",
    "updated": 0
  },
  {
    "data": [
      {
        "text": "preciso descartar ",
        "userDefined": false
      },
      {
        "text": "latinha",
        "meta": "@metal_lixo",
        "alias": "metal_lixo",
        "userDefined": false
      },
      {
        "text": " de refrigerante",
        "userDefined": false
      }
    ],
    "isTemplate": false,
    "count": 1,
    "lang": "pt-br",
    "updated": 0
  },
  {
    "data": [
      {
        "text": "onde jogo ",
        "userDefined": false
      },
      {
        "text": "lata de sardinha",
        "meta": "@metal_lixo",
        "alias": "metal_lixo",
        "userDefined": false
      }
    ],
    "isTemplate": false,
    "count": 1,
    "lang": "pt-br",
    "updated": 0
  },
  {
    "data": [
      {
        "text": "Preciso descartar ",
        "userDefined": false
      },
      {
        "text": "papel alumínio",
        "meta": "@metal_lixo",
        "alias": "metal_lixo",
        "userDefined": false
      }
    ],
    "isTemplate": false,
    "count": 0,
    "lang": "pt-br",
    "updated": 0
  },
  {
    "id": "f2bfb82f-6d9e-4059-bec7-c568cad56196",
    "data": [
      {
        "text": "onde jogo metal",
        "userDefined": false
      }
    ],
    "isTemplate": false,
    "count": 0,
    "lang": "pt-br",
    "updated": 0
  },
  {
    "id": "7ae51895-fe15-4b12-910e-331e3e7935e4",
    "data": [
      {
        "text": "como descartar metal",
        "userDefined": false
      }
    ],
    "isTemplate": false,
    "count": 0,
    "lang": "pt-br",
    "updated": 0
  },
  {
    "id": "93b78f6a-a85b-426e-8a9c-413e6948caa5",
    "data": [
      {
        "text": "descarta lata de aluminio",
        "userDefined": false
      }
    ],
    "isTemplate": false,
    "count": 0,
    "lang": "pt-br",
    "updated": 0
  },
  {
    "id": "4f664252-5f47-4986-b896-bf1d46f1d723",
    "data": [
      {
        "text": "onde coloco lata de refrigerante",
        "userDefined": false
      }
    ],
    "isTemplate": false,
    "count": 0,
    "lang": "pt-br",
    "updated": 0
  },
  {
    "id": "0cbff770-9fd0-4027-92c8-2b84ed28cf16",
    "data": [
      {
        "text": "qual lixeira para lata",
        "userDefined": false
      }
    ],
    "isTemplate": false,
    "count": 0,
    "lang": "pt-br",
    "updated": 0
  },
  {
    "id": "fb806bd3-487d-4850-843f-b66eea2c9a80",
    "data": [
      {
        "text": "preciso descartar lata de alumínio",
        "userDefined": false
      }
    ],
    "isTemplate": false,
    "count": 0,
    "lang": "pt-br",
    "updated": 0
  },
  {
    "id": "39181ef9-cbfb-4d93-9426-82ba62084b77",
    "data": [
      {
        "text": "onde descarto lata de cerveja",
        "userDefined": false
      }
    ],
    "isTemplate": false,
    "count": 0,
    "lang": "pt-br",
    "updated": 0
  },
  {
    "id": "497d1d73-2ea8-4162-ba32-63b927223924",
    "data": [
      {
        "text": "como descartar lata de cerveja",
        "userDefined": false
      }
    ],
    "isTemplate": false,
    "count": 0,
    "lang": "pt-br",
    "updated": 0
  },
  {
    "id": "f07eacd3-5ca8-44b6-85b0-d0e8a771f30b",
    "data": [
      {
        "text": "lata vai para reciclagem",
        "userDefined": false
      }
    ],
    "isTemplate": false,
    "count": 0,
    "lang": "pt-br",
    "updated": 0
  },
  {
    "id": "e934d558-5d8f-4231-a053-8208a8d097ee",
    "data": [
      {
        "text": "onde jogo lata de sardinha",
        "userDefined": false
      }
    ],
    "isTemplate": false,
    "count": 0,
    "lang": "pt-br",
    "updated": 0
  },
  {
    "id": "0d47eeb4-3020-49e7-b01e-40c20d9e67f5",
    "data": [
      {
        "text": "descarta caixa de metal",
        "userDefined": false
      }
    ],
    "isTemplate": false,
    "count": 0,
    "lang": "pt-br",
    "updated": 0
  },
  {
    "id": "a3e55ab2-89f7-4d47-858e-2f178e4f7eda",
    "data": [
      {
        "text": "onde coloco/tampa de metal",
        "userDefined": false
      }
    ],
    "isTemplate": false,
    "count": 0,
    "lang": "pt-br",
    "updated": 0
  },
  {
    "id": "90d39b43-b668-4784-9824-31a1fb6d34bf",
    "data": [
      {
        "text": "como descartar aluminio",
        "userDefined": false
      }
    ],
    "isTemplate": false,
    "count": 0,
    "lang": "pt-br",
    "updated": 0
  },
  {
    "id": "41323fd4-4e47-42a7-a1b9-7d136ced4dc7",
    "data": [
      {
        "text": "preciso me livrar de metal",
        "userDefined": false
      }
    ],
    "isTemplate": false,
    "count": 0,
    "lang": "pt-br",
    "updated": 0
  },
  {
    "id": "de8945c3-7d2d-46a4-ad4d-456602ab7105",
    "data": [
      {
        "text": "reciclagem de metal",
        "userDefined": false
      }
    ],
    "isTemplate": false,
    "count": 0,
    "lang": "pt-br",
    "updated": 0
  },
  {
    "id": "bb5559d7-2a04-4f9d-bd11-2fd533589eea",
    "data": [
      {
        "text": "onde jogo ferragem",
        "userDefined": false
      }
    ],
    "isTemplate": false,
    "count": 0,
    "lang": "pt-br",
    "updated": 0
  },
  {
    "id": "b54d5a51-7df4-434d-87c6-03b492da5e59",
    "data": [
      {
        "text": "descarta prego",
        "userDefined": false
      }
    ],
    "isTemplate": false,
    "count": 0,
    "lang": "pt-br",
    "updated": 0
  },
  {
    "id": "34d74b6f-9103-4e6f-8e4b-e398ab27dc54",
    "data": [
      {
        "text": "onde coloco arame",
        "userDefined": false
      }
    ],
    "isTemplate": false,
    "count": 0,
    "lang": "pt-br",
    "updated": 0
  },
  {
    "id": "4cd3ecd5-d616-4b2f-ac58-60fe462564a5",
    "data": [
      {
        "text": "como descartar fios de cobre",
        "userDefined": false
      }
    ],
    "isTemplate": false,
    "count": 0,
    "lang": "pt-br",
    "updated": 0
  }
]